{
	"entries": [
		{
				"handlerName": "on_startregulartests",
				"timestamp": "2024-06-07 13:56:14.478 -0400",
				"message": "Running TestCases/Regular/verifyToolsMenu.script",
				"scriptName": "TestCases/Regular/testLauncher.script",
				"handlerLine": 22,
				"identifier": "START"
			},
		{
				"handlerName": "on_verifytoolsmenu",
				"timestamp": "2024-06-07 13:56:14.534 -0400",
				"message": "verifyToolsMenu",
				"scriptName": "TestCases/Regular/verifyToolsMenu.script",
				"handlerLine": 2,
				"identifier": "BeginTestCase"
			},
		{
				"handlerName": "on_compare_screen",
				"timestamp": "2024-06-07 13:56:14.791 -0400",
				"scriptName": "Common/check.script",
				"message": "CompareScreen \"GUI_Canvas_Windows7 6 2024 _ 13 41 18\" -- No significant differences from baseline",
				"image": "[Baseline_Screens]/GUI_Canvas_Windows7 6 2024 _ 13 41 18.png",
				"handlerLine": 3,
				"identifier": "CompareScreen"
			},
		{
				"handlerName": "function_compare_screen",
				"timestamp": "2024-06-07 13:56:14.912 -0400",
				"scriptName": "Common/check.script",
				"message": "CompareScreen \"GUI_Canvas_Windows7 6 2024 _ 13 41 18\" -- No significant differences from baseline",
				"image": "[Baseline_Screens]/GUI_Canvas_Windows7 6 2024 _ 13 41 18.png",
				"handlerLine": 3,
				"identifier": "CompareScreen"
			},
		{
				"handlerName": "on_setsearchsection",
				"timestamp": "2024-06-07 13:56:15.289 -0400",
				"message": "SEARCHRECTANGLE = [[96,18.36],[347.52,590.76]]",
				"scriptName": "Common/search.script",
				"handlerLine": 3,
				"identifier": "set"
			},
		{
				"handlerName": "on_leftevent",
				"timestamp": "2024-06-07 13:56:18.056 -0400",
				"scriptName": "Common/clickEvent.script",
				"message": "at (122, 31)",
				"image": "(TEXT:\"Tools\")",
				"handlerLine": 6,
				"identifier": "click"
			},
		{
				"handlerName": "function_isimagetextfound",
				"timestamp": "2024-06-07 13:56:21.689 -0400",
				"scriptName": "Common/check.script",
				"message": "found at (176, 54)",
				"image": "(TEXT:\"Node Placement\")",
				"handlerLine": 9,
				"identifier": "imagefound"
			},
		{
				"handlerName": "function_isimagetextfound",
				"timestamp": "2024-06-07 13:56:22.133 -0400",
				"scriptName": "Common/check.script",
				"message": "at (176, 54)",
				"image": "(TEXT:\"Node Placement\")",
				"handlerLine": 10,
				"identifier": "moveto"
			},
		{
				"handlerName": "on_success",
				"timestamp": "2024-06-07 13:56:22.202 -0400",
				"message": "Node Placement  is found in ",
				"scriptName": "Common/cLog.script",
				"handlerLine": 2,
				"identifier": "LogSuccess"
			},
		{
				"handlerName": "on_clearsearchsection",
				"timestamp": "2024-06-07 13:56:22.272 -0400",
				"message": "SEARCHRECTANGLE = ",
				"scriptName": "Common/search.script",
				"handlerLine": 2,
				"identifier": "set"
			},
		{
				"handlerName": "on_success",
				"timestamp": "2024-06-07 13:56:22.399 -0400",
				"message": "Tools menu opened successfully",
				"scriptName": "Common/cLog.script",
				"handlerLine": 2,
				"identifier": "LogSuccess"
			},
		{
				"handlerName": "on_capturescreenshots",
				"timestamp": "2024-06-07 13:56:22.514 -0400",
				"scriptName": "Common/captureScreenShots.script",
				"message": "(0,2,792,735)",
				"image": "verifyToolsMenu.png",
				"handlerLine": 4,
				"identifier": "capturescreen"
			},
		{
				"handlerName": "on_setsearchsection",
				"timestamp": "2024-06-07 13:56:22.989 -0400",
				"message": "SEARCHRECTANGLE = [[96,18.36],[347.52,590.76]]",
				"scriptName": "Common/search.script",
				"handlerLine": 3,
				"identifier": "set"
			},
		{
				"handlerName": "on_isimagetextfound",
				"timestamp": "2024-06-07 13:56:23.282 -0400",
				"scriptName": "Common/check.script",
				"message": "found at (176, 54)",
				"image": "(TEXT:\"Node Placement\")",
				"handlerLine": 9,
				"identifier": "imagefound"
			},
		{
				"handlerName": "on_isimagetextfound",
				"timestamp": "2024-06-07 13:56:23.578 -0400",
				"scriptName": "Common/check.script",
				"message": "at (176, 54)",
				"image": "(TEXT:\"Node Placement\")",
				"handlerLine": 10,
				"identifier": "moveto"
			},
		{
				"handlerName": "on_success",
				"timestamp": "2024-06-07 13:56:23.650 -0400",
				"message": "Node Placement  is found in ToolsMenu",
				"scriptName": "Common/cLog.script",
				"handlerLine": 2,
				"identifier": "LogSuccess"
			},
		{
				"handlerName": "on_clearsearchsection",
				"timestamp": "2024-06-07 13:56:23.765 -0400",
				"message": "SEARCHRECTANGLE = ",
				"scriptName": "Common/search.script",
				"handlerLine": 2,
				"identifier": "set"
			},
		{
				"handlerName": "on_setsearchsection",
				"timestamp": "2024-06-07 13:56:24.156 -0400",
				"message": "SEARCHRECTANGLE = [[96,18.36],[347.52,590.76]]",
				"scriptName": "Common/search.script",
				"handlerLine": 3,
				"identifier": "set"
			},
		{
				"handlerName": "on_isimagetextfound",
				"timestamp": "2024-06-07 13:56:24.507 -0400",
				"scriptName": "Common/check.script",
				"message": "found at (203, 77)",
				"image": "(TEXT:\"Import Satellites and Orbits\")",
				"handlerLine": 9,
				"identifier": "imagefound"
			},
		{
				"handlerName": "on_isimagetextfound",
				"timestamp": "2024-06-07 13:56:24.948 -0400",
				"scriptName": "Common/check.script",
				"message": "at (203, 77)",
				"image": "(TEXT:\"Import Satellites and Orbits\")",
				"handlerLine": 10,
				"identifier": "moveto"
			},
		{
				"handlerName": "on_success",
				"timestamp": "2024-06-07 13:56:24.991 -0400",
				"message": "Import Satellites and Orbits  is found in ToolsMenu",
				"scriptName": "Common/cLog.script",
				"handlerLine": 2,
				"identifier": "LogSuccess"
			},
		{
				"handlerName": "on_clearsearchsection",
				"timestamp": "2024-06-07 13:56:25.049 -0400",
				"message": "SEARCHRECTANGLE = ",
				"scriptName": "Common/search.script",
				"handlerLine": 2,
				"identifier": "set"
			},
		{
				"handlerName": "on_setsearchsection",
				"timestamp": "2024-06-07 13:56:25.406 -0400",
				"message": "SEARCHRECTANGLE = [[96,18.36],[347.52,590.76]]",
				"scriptName": "Common/search.script",
				"handlerLine": 3,
				"identifier": "set"
			},
		{
				"handlerName": "on_isimagetextfound",
				"timestamp": "2024-06-07 13:56:25.772 -0400",
				"scriptName": "Common/check.script",
				"message": "found at (160, 99)",
				"image": "(TEXT:\"Snapshot\")",
				"handlerLine": 9,
				"identifier": "imagefound"
			},
		{
				"handlerName": "on_isimagetextfound",
				"timestamp": "2024-06-07 13:56:26.334 -0400",
				"scriptName": "Common/check.script",
				"message": "at (160, 99)",
				"image": "(TEXT:\"Snapshot\")",
				"handlerLine": 10,
				"identifier": "moveto"
			},
		{
				"handlerName": "on_success",
				"timestamp": "2024-06-07 13:56:26.407 -0400",
				"message": "Snapshot  is found in ToolsMenu",
				"scriptName": "Common/cLog.script",
				"handlerLine": 2,
				"identifier": "LogSuccess"
			},
		{
				"handlerName": "on_clearsearchsection",
				"timestamp": "2024-06-07 13:56:26.470 -0400",
				"message": "SEARCHRECTANGLE = ",
				"scriptName": "Common/search.script",
				"handlerLine": 2,
				"identifier": "set"
			},
		{
				"handlerName": "on_setsearchsection",
				"timestamp": "2024-06-07 13:56:26.895 -0400",
				"message": "SEARCHRECTANGLE = [[96,18.36],[347.52,590.76]]",
				"scriptName": "Common/search.script",
				"handlerLine": 3,
				"identifier": "set"
			},
		{
				"handlerName": "on_isimagetextfound",
				"timestamp": "2024-06-07 13:56:27.316 -0400",
				"scriptName": "Common/check.script",
				"message": "found at (201, 129)",
				"image": "(TEXT:\"View Scenario in File Editor\")",
				"handlerLine": 9,
				"identifier": "imagefound"
			},
		{
				"handlerName": "on_isimagetextfound",
				"timestamp": "2024-06-07 13:56:27.851 -0400",
				"scriptName": "Common/check.script",
				"message": "at (201, 129)",
				"image": "(TEXT:\"View Scenario in File Editor\")",
				"handlerLine": 10,
				"identifier": "moveto"
			},
		{
				"handlerName": "on_success",
				"timestamp": "2024-06-07 13:56:27.916 -0400",
				"message": "View Scenario in File Editor  is found in ToolsMenu",
				"scriptName": "Common/cLog.script",
				"handlerLine": 2,
				"identifier": "LogSuccess"
			},
		{
				"handlerName": "on_clearsearchsection",
				"timestamp": "2024-06-07 13:56:27.985 -0400",
				"message": "SEARCHRECTANGLE = ",
				"scriptName": "Common/search.script",
				"handlerLine": 2,
				"identifier": "set"
			},
		{
				"handlerName": "on_setsearchsection",
				"timestamp": "2024-06-07 13:56:28.372 -0400",
				"message": "SEARCHRECTANGLE = [[96,18.36],[347.52,590.76]]",
				"scriptName": "Common/search.script",
				"handlerLine": 3,
				"identifier": "set"
			},
		{
				"handlerName": "on_isimagetextfound",
				"timestamp": "2024-06-07 13:56:28.737 -0400",
				"scriptName": "Common/check.script",
				"message": "found at (168, 153)",
				"image": "(TEXT:\"Run Settings\")",
				"handlerLine": 9,
				"identifier": "imagefound"
			},
		{
				"handlerName": "on_isimagetextfound",
				"timestamp": "2024-06-07 13:56:29.300 -0400",
				"scriptName": "Common/check.script",
				"message": "at (168, 153)",
				"image": "(TEXT:\"Run Settings\")",
				"handlerLine": 10,
				"identifier": "moveto"
			},
		{
				"handlerName": "on_success",
				"timestamp": "2024-06-07 13:56:29.350 -0400",
				"message": "Run Settings  is found in ToolsMenu",
				"scriptName": "Common/cLog.script",
				"handlerLine": 2,
				"identifier": "LogSuccess"
			},
		{
				"handlerName": "on_clearsearchsection",
				"timestamp": "2024-06-07 13:56:29.418 -0400",
				"message": "SEARCHRECTANGLE = ",
				"scriptName": "Common/search.script",
				"handlerLine": 2,
				"identifier": "set"
			},
		{
				"handlerName": "on_setsearchsection",
				"timestamp": "2024-06-07 13:56:29.797 -0400",
				"message": "SEARCHRECTANGLE = [[96,18.36],[347.52,590.76]]",
				"scriptName": "Common/search.script",
				"handlerLine": 3,
				"identifier": "set"
			},
		{
				"handlerName": "on_isimagetextfound",
				"timestamp": "2024-06-07 13:56:30.284 -0400",
				"scriptName": "Common/check.script",
				"message": "found at (171, 173)",
				"image": "(TEXT:\"Run Emulation\")",
				"handlerLine": 9,
				"identifier": "imagefound"
			},
		{
				"handlerName": "on_isimagetextfound",
				"timestamp": "2024-06-07 13:56:30.794 -0400",
				"scriptName": "Common/check.script",
				"message": "at (171, 173)",
				"image": "(TEXT:\"Run Emulation\")",
				"handlerLine": 10,
				"identifier": "moveto"
			},
		{
				"handlerName": "on_success",
				"timestamp": "2024-06-07 13:56:30.849 -0400",
				"message": "Run Emulation  is found in ToolsMenu",
				"scriptName": "Common/cLog.script",
				"handlerLine": 2,
				"identifier": "LogSuccess"
			},
		{
				"handlerName": "on_clearsearchsection",
				"timestamp": "2024-06-07 13:56:30.931 -0400",
				"message": "SEARCHRECTANGLE = ",
				"scriptName": "Common/search.script",
				"handlerLine": 2,
				"identifier": "set"
			},
		{
				"handlerName": "on_setsearchsection",
				"timestamp": "2024-06-07 13:56:31.294 -0400",
				"message": "SEARCHRECTANGLE = [[96,18.36],[347.52,590.76]]",
				"scriptName": "Common/search.script",
				"handlerLine": 3,
				"identifier": "set"
			},
		{
				"handlerName": "on_isimagetextfound",
				"timestamp": "2024-06-07 13:56:31.732 -0400",
				"scriptName": "Common/check.script",
				"message": "found at (179, 195)",
				"image": "(TEXT:\"Record Animation\")",
				"handlerLine": 9,
				"identifier": "imagefound"
			},
		{
				"handlerName": "on_isimagetextfound",
				"timestamp": "2024-06-07 13:56:32.213 -0400",
				"scriptName": "Common/check.script",
				"message": "at (179, 195)",
				"image": "(TEXT:\"Record Animation\")",
				"handlerLine": 10,
				"identifier": "moveto"
			},
		{
				"handlerName": "on_success",
				"timestamp": "2024-06-07 13:56:32.259 -0400",
				"message": "Record Animation  is found in ToolsMenu",
				"scriptName": "Common/cLog.script",
				"handlerLine": 2,
				"identifier": "LogSuccess"
			},
		{
				"handlerName": "on_clearsearchsection",
				"timestamp": "2024-06-07 13:56:32.320 -0400",
				"message": "SEARCHRECTANGLE = ",
				"scriptName": "Common/search.script",
				"handlerLine": 2,
				"identifier": "set"
			},
		{
				"handlerName": "on_setsearchsection",
				"timestamp": "2024-06-07 13:56:32.724 -0400",
				"message": "SEARCHRECTANGLE = [[96,18.36],[347.52,590.76]]",
				"scriptName": "Common/search.script",
				"handlerLine": 3,
				"identifier": "set"
			},
		{
				"handlerName": "on_isimagetextfound",
				"timestamp": "2024-06-07 13:56:33.096 -0400",
				"scriptName": "Common/check.script",
				"message": "found at (184, 226)",
				"image": "(TEXT:\"Device Model Editor\")",
				"handlerLine": 9,
				"identifier": "imagefound"
			},
		{
				"handlerName": "on_isimagetextfound",
				"timestamp": "2024-06-07 13:56:33.563 -0400",
				"scriptName": "Common/check.script",
				"message": "at (184, 226)",
				"image": "(TEXT:\"Device Model Editor\")",
				"handlerLine": 10,
				"identifier": "moveto"
			},
		{
				"handlerName": "on_success",
				"timestamp": "2024-06-07 13:56:33.608 -0400",
				"message": "Device Model Editor  is found in ToolsMenu",
				"scriptName": "Common/cLog.script",
				"handlerLine": 2,
				"identifier": "LogSuccess"
			},
		{
				"handlerName": "on_clearsearchsection",
				"timestamp": "2024-06-07 13:56:33.688 -0400",
				"message": "SEARCHRECTANGLE = ",
				"scriptName": "Common/search.script",
				"handlerLine": 2,
				"identifier": "set"
			},
		{
				"handlerName": "on_setsearchsection",
				"timestamp": "2024-06-07 13:56:34.052 -0400",
				"message": "SEARCHRECTANGLE = [[96,18.36],[347.52,590.76]]",
				"scriptName": "Common/search.script",
				"handlerLine": 3,
				"identifier": "set"
			},
		{
				"handlerName": "on_isimagetextfound",
				"timestamp": "2024-06-07 13:56:34.412 -0400",
				"scriptName": "Common/check.script",
				"message": "found at (191, 249)",
				"image": "(TEXT:\"Hierarchy Model Editor\")",
				"handlerLine": 9,
				"identifier": "imagefound"
			},
		{
				"handlerName": "on_isimagetextfound",
				"timestamp": "2024-06-07 13:56:34.926 -0400",
				"scriptName": "Common/check.script",
				"message": "at (191, 249)",
				"image": "(TEXT:\"Hierarchy Model Editor\")",
				"handlerLine": 10,
				"identifier": "moveto"
			},
		{
				"handlerName": "on_success",
				"timestamp": "2024-06-07 13:56:34.978 -0400",
				"message": "Hierarchy Model Editor  is found in ToolsMenu",
				"scriptName": "Common/cLog.script",
				"handlerLine": 2,
				"identifier": "LogSuccess"
			},
		{
				"handlerName": "on_clearsearchsection",
				"timestamp": "2024-06-07 13:56:35.040 -0400",
				"message": "SEARCHRECTANGLE = ",
				"scriptName": "Common/search.script",
				"handlerLine": 2,
				"identifier": "set"
			},
		{
				"handlerName": "on_setsearchsection",
				"timestamp": "2024-06-07 13:56:35.420 -0400",
				"message": "SEARCHRECTANGLE = [[96,18.36],[347.52,590.76]]",
				"scriptName": "Common/search.script",
				"handlerLine": 3,
				"identifier": "set"
			},
		{
				"handlerName": "on_isimagetextfound",
				"timestamp": "2024-06-07 13:56:35.784 -0400",
				"scriptName": "Common/check.script",
				"message": "found at (170, 270)",
				"image": "(TEXT:\"Toolset Editor\")",
				"handlerLine": 9,
				"identifier": "imagefound"
			},
		{
				"handlerName": "on_isimagetextfound",
				"timestamp": "2024-06-07 13:56:36.297 -0400",
				"scriptName": "Common/check.script",
				"message": "at (170, 270)",
				"image": "(TEXT:\"Toolset Editor\")",
				"handlerLine": 10,
				"identifier": "moveto"
			},
		{
				"handlerName": "on_success",
				"timestamp": "2024-06-07 13:56:36.337 -0400",
				"message": "Toolset Editor  is found in ToolsMenu",
				"scriptName": "Common/cLog.script",
				"handlerLine": 2,
				"identifier": "LogSuccess"
			},
		{
				"handlerName": "on_clearsearchsection",
				"timestamp": "2024-06-07 13:56:36.404 -0400",
				"message": "SEARCHRECTANGLE = ",
				"scriptName": "Common/search.script",
				"handlerLine": 2,
				"identifier": "set"
			},
		{
				"handlerName": "on_setsearchsection",
				"timestamp": "2024-06-07 13:56:36.799 -0400",
				"message": "SEARCHRECTANGLE = [[96,18.36],[347.52,590.76]]",
				"scriptName": "Common/search.script",
				"handlerLine": 3,
				"identifier": "set"
			},
		{
				"handlerName": "on_isimagetextfound",
				"timestamp": "2024-06-07 13:56:37.151 -0400",
				"scriptName": "Common/check.script",
				"message": "found at (190, 293)",
				"image": "(TEXT:\"Multicast Group Editor\")",
				"handlerLine": 9,
				"identifier": "imagefound"
			},
		{
				"handlerName": "on_isimagetextfound",
				"timestamp": "2024-06-07 13:56:37.653 -0400",
				"scriptName": "Common/check.script",
				"message": "at (190, 293)",
				"image": "(TEXT:\"Multicast Group Editor\")",
				"handlerLine": 10,
				"identifier": "moveto"
			},
		{
				"handlerName": "on_success",
				"timestamp": "2024-06-07 13:56:37.697 -0400",
				"message": "Multicast Group Editor  is found in ToolsMenu",
				"scriptName": "Common/cLog.script",
				"handlerLine": 2,
				"identifier": "LogSuccess"
			},
		{
				"handlerName": "on_clearsearchsection",
				"timestamp": "2024-06-07 13:56:37.763 -0400",
				"message": "SEARCHRECTANGLE = ",
				"scriptName": "Common/search.script",
				"handlerLine": 2,
				"identifier": "set"
			},
		{
				"handlerName": "on_setsearchsection",
				"timestamp": "2024-06-07 13:56:38.126 -0400",
				"message": "SEARCHRECTANGLE = [[96,18.36],[347.52,590.76]]",
				"scriptName": "Common/search.script",
				"handlerLine": 3,
				"identifier": "set"
			},
		{
				"handlerName": "on_isimagetextfound",
				"timestamp": "2024-06-07 13:56:38.499 -0400",
				"scriptName": "Common/check.script",
				"message": "found at (189, 314)",
				"image": "(TEXT:\"Antenna Model Editor\")",
				"handlerLine": 9,
				"identifier": "imagefound"
			},
		{
				"handlerName": "on_isimagetextfound",
				"timestamp": "2024-06-07 13:56:39.038 -0400",
				"scriptName": "Common/check.script",
				"message": "at (189, 314)",
				"image": "(TEXT:\"Antenna Model Editor\")",
				"handlerLine": 10,
				"identifier": "moveto"
			},
		{
				"handlerName": "on_success",
				"timestamp": "2024-06-07 13:56:39.087 -0400",
				"message": "Antenna Model Editor  is found in ToolsMenu",
				"scriptName": "Common/cLog.script",
				"handlerLine": 2,
				"identifier": "LogSuccess"
			},
		{
				"handlerName": "on_clearsearchsection",
				"timestamp": "2024-06-07 13:56:39.147 -0400",
				"message": "SEARCHRECTANGLE = ",
				"scriptName": "Common/search.script",
				"handlerLine": 2,
				"identifier": "set"
			},
		{
				"handlerName": "on_setsearchsection",
				"timestamp": "2024-06-07 13:56:39.535 -0400",
				"message": "SEARCHRECTANGLE = [[96,18.36],[347.52,590.76]]",
				"scriptName": "Common/search.script",
				"handlerLine": 3,
				"identifier": "set"
			},
		{
				"handlerName": "on_isimagetextfound",
				"timestamp": "2024-06-07 13:56:39.916 -0400",
				"scriptName": "Common/check.script",
				"message": "found at (180, 337)",
				"image": "(TEXT:\"Visualize Heatmap\")",
				"handlerLine": 9,
				"identifier": "imagefound"
			},
		{
				"handlerName": "on_isimagetextfound",
				"timestamp": "2024-06-07 13:56:40.362 -0400",
				"scriptName": "Common/check.script",
				"message": "at (180, 337)",
				"image": "(TEXT:\"Visualize Heatmap\")",
				"handlerLine": 10,
				"identifier": "moveto"
			},
		{
				"handlerName": "on_success",
				"timestamp": "2024-06-07 13:56:40.403 -0400",
				"message": "Visualize Heatmap  is found in ToolsMenu",
				"scriptName": "Common/cLog.script",
				"handlerLine": 2,
				"identifier": "LogSuccess"
			},
		{
				"handlerName": "on_clearsearchsection",
				"timestamp": "2024-06-07 13:56:40.477 -0400",
				"message": "SEARCHRECTANGLE = ",
				"scriptName": "Common/search.script",
				"handlerLine": 2,
				"identifier": "set"
			},
		{
				"handlerName": "on_setsearchsection",
				"timestamp": "2024-06-07 13:56:40.854 -0400",
				"message": "SEARCHRECTANGLE = [[96,18.36],[347.52,590.76]]",
				"scriptName": "Common/search.script",
				"handlerLine": 3,
				"identifier": "set"
			},
		{
				"handlerName": "on_isimagetextfound",
				"timestamp": "2024-06-07 13:56:41.217 -0400",
				"scriptName": "Common/check.script",
				"message": "found at (192, 359)",
				"image": "(TEXT:\"Attack Template Editor\")",
				"handlerLine": 9,
				"identifier": "imagefound"
			},
		{
				"handlerName": "on_isimagetextfound",
				"timestamp": "2024-06-07 13:56:41.717 -0400",
				"scriptName": "Common/check.script",
				"message": "at (192, 359)",
				"image": "(TEXT:\"Attack Template Editor\")",
				"handlerLine": 10,
				"identifier": "moveto"
			},
		{
				"handlerName": "on_success",
				"timestamp": "2024-06-07 13:56:41.767 -0400",
				"message": "Attack Template Editor  is found in ToolsMenu",
				"scriptName": "Common/cLog.script",
				"handlerLine": 2,
				"identifier": "LogSuccess"
			},
		{
				"handlerName": "on_clearsearchsection",
				"timestamp": "2024-06-07 13:56:41.833 -0400",
				"message": "SEARCHRECTANGLE = ",
				"scriptName": "Common/search.script",
				"handlerLine": 2,
				"identifier": "set"
			},
		{
				"handlerName": "on_setsearchsection",
				"timestamp": "2024-06-07 13:56:42.208 -0400",
				"message": "SEARCHRECTANGLE = [[96,18.36],[347.52,590.76]]",
				"scriptName": "Common/search.script",
				"handlerLine": 3,
				"identifier": "set"
			},
		{
				"handlerName": "on_isimagetextfound",
				"timestamp": "2024-06-07 13:56:42.577 -0400",
				"scriptName": "Common/check.script",
				"message": "found at (187, 381)",
				"image": "(TEXT:\"Import Firewall Rules\")",
				"handlerLine": 9,
				"identifier": "imagefound"
			},
		{
				"handlerName": "on_isimagetextfound",
				"timestamp": "2024-06-07 13:56:43.103 -0400",
				"scriptName": "Common/check.script",
				"message": "at (187, 381)",
				"image": "(TEXT:\"Import Firewall Rules\")",
				"handlerLine": 10,
				"identifier": "moveto"
			},
		{
				"handlerName": "on_success",
				"timestamp": "2024-06-07 13:56:43.154 -0400",
				"message": "Import Firewall Rules  is found in ToolsMenu",
				"scriptName": "Common/cLog.script",
				"handlerLine": 2,
				"identifier": "LogSuccess"
			},
		{
				"handlerName": "on_clearsearchsection",
				"timestamp": "2024-06-07 13:56:43.242 -0400",
				"message": "SEARCHRECTANGLE = ",
				"scriptName": "Common/search.script",
				"handlerLine": 2,
				"identifier": "set"
			},
		{
				"handlerName": "on_setsearchsection",
				"timestamp": "2024-06-07 13:56:43.611 -0400",
				"message": "SEARCHRECTANGLE = [[96,18.36],[347.52,590.76]]",
				"scriptName": "Common/search.script",
				"handlerLine": 3,
				"identifier": "set"
			},
		{
				"handlerName": "on_isimagetextfound",
				"timestamp": "2024-06-07 13:56:43.989 -0400",
				"scriptName": "Common/check.script",
				"message": "found at (209, 403)",
				"image": "(TEXT:\"PROPSIM Configuration Editor\")",
				"handlerLine": 9,
				"identifier": "imagefound"
			},
		{
				"handlerName": "on_isimagetextfound",
				"timestamp": "2024-06-07 13:56:44.461 -0400",
				"scriptName": "Common/check.script",
				"message": "at (209, 403)",
				"image": "(TEXT:\"PROPSIM Configuration Editor\")",
				"handlerLine": 10,
				"identifier": "moveto"
			},
		{
				"handlerName": "on_success",
				"timestamp": "2024-06-07 13:56:44.515 -0400",
				"message": "PROPSIM Configuration Editor  is found in ToolsMenu",
				"scriptName": "Common/cLog.script",
				"handlerLine": 2,
				"identifier": "LogSuccess"
			},
		{
				"handlerName": "on_clearsearchsection",
				"timestamp": "2024-06-07 13:56:44.571 -0400",
				"message": "SEARCHRECTANGLE = ",
				"scriptName": "Common/search.script",
				"handlerLine": 2,
				"identifier": "set"
			},
		{
				"handlerName": "on_setsearchsection",
				"timestamp": "2024-06-07 13:56:44.977 -0400",
				"message": "SEARCHRECTANGLE = [[96,18.36],[347.52,590.76]]",
				"scriptName": "Common/search.script",
				"handlerLine": 3,
				"identifier": "set"
			},
		{
				"handlerName": "on_isimagetextfound",
				"timestamp": "2024-06-07 13:56:45.352 -0400",
				"scriptName": "Common/check.script",
				"message": "found at (216, 425)",
				"image": "(TEXT:\"Adaptive Attack Flowchart Editor\")",
				"handlerLine": 9,
				"identifier": "imagefound"
			},
		{
				"handlerName": "on_isimagetextfound",
				"timestamp": "2024-06-07 13:56:45.800 -0400",
				"scriptName": "Common/check.script",
				"message": "at (216, 425)",
				"image": "(TEXT:\"Adaptive Attack Flowchart Editor\")",
				"handlerLine": 10,
				"identifier": "moveto"
			},
		{
				"handlerName": "on_success",
				"timestamp": "2024-06-07 13:56:45.848 -0400",
				"message": "Adaptive Attack Flowchart Editor  is found in ToolsMenu",
				"scriptName": "Common/cLog.script",
				"handlerLine": 2,
				"identifier": "LogSuccess"
			},
		{
				"handlerName": "on_clearsearchsection",
				"timestamp": "2024-06-07 13:56:45.912 -0400",
				"message": "SEARCHRECTANGLE = ",
				"scriptName": "Common/search.script",
				"handlerLine": 2,
				"identifier": "set"
			},
		{
				"handlerName": "on_setsearchsection",
				"timestamp": "2024-06-07 13:56:46.287 -0400",
				"message": "SEARCHRECTANGLE = [[96,18.36],[347.52,590.76]]",
				"scriptName": "Common/search.script",
				"handlerLine": 3,
				"identifier": "set"
			},
		{
				"handlerName": "on_isimagetextfound",
				"timestamp": "2024-06-07 13:56:46.646 -0400",
				"scriptName": "Common/check.script",
				"message": "found at (186, 455)",
				"image": "(TEXT:\"Modified Parameters\")",
				"handlerLine": 9,
				"identifier": "imagefound"
			},
		{
				"handlerName": "on_isimagetextfound",
				"timestamp": "2024-06-07 13:56:47.196 -0400",
				"scriptName": "Common/check.script",
				"message": "at (186, 455)",
				"image": "(TEXT:\"Modified Parameters\")",
				"handlerLine": 10,
				"identifier": "moveto"
			},
		{
				"handlerName": "on_success",
				"timestamp": "2024-06-07 13:56:47.245 -0400",
				"message": "Modified Parameters  is found in ToolsMenu",
				"scriptName": "Common/cLog.script",
				"handlerLine": 2,
				"identifier": "LogSuccess"
			},
		{
				"handlerName": "on_clearsearchsection",
				"timestamp": "2024-06-07 13:56:47.310 -0400",
				"message": "SEARCHRECTANGLE = ",
				"scriptName": "Common/search.script",
				"handlerLine": 2,
				"identifier": "set"
			},
		{
				"handlerName": "on_setsearchsection",
				"timestamp": "2024-06-07 13:56:47.709 -0400",
				"message": "SEARCHRECTANGLE = [[96,18.36],[347.52,590.76]]",
				"scriptName": "Common/search.script",
				"handlerLine": 3,
				"identifier": "set"
			},
		{
				"handlerName": "on_isimagetextfound",
				"timestamp": "2024-06-07 13:56:48.071 -0400",
				"scriptName": "Common/check.script",
				"message": "found at (184, 478)",
				"image": "(TEXT:\"Weather Properties\")",
				"handlerLine": 9,
				"identifier": "imagefound"
			},
		{
				"handlerName": "on_isimagetextfound",
				"timestamp": "2024-06-07 13:56:48.565 -0400",
				"scriptName": "Common/check.script",
				"message": "at (184, 478)",
				"image": "(TEXT:\"Weather Properties\")",
				"handlerLine": 10,
				"identifier": "moveto"
			},
		{
				"handlerName": "on_success",
				"timestamp": "2024-06-07 13:56:48.620 -0400",
				"message": "Weather Properties  is found in ToolsMenu",
				"scriptName": "Common/cLog.script",
				"handlerLine": 2,
				"identifier": "LogSuccess"
			},
		{
				"handlerName": "on_clearsearchsection",
				"timestamp": "2024-06-07 13:56:48.679 -0400",
				"message": "SEARCHRECTANGLE = ",
				"scriptName": "Common/search.script",
				"handlerLine": 2,
				"identifier": "set"
			},
		{
				"handlerName": "on_setsearchsection",
				"timestamp": "2024-06-07 13:56:49.119 -0400",
				"message": "SEARCHRECTANGLE = [[96,18.36],[347.52,590.76]]",
				"scriptName": "Common/search.script",
				"handlerLine": 3,
				"identifier": "set"
			},
		{
				"handlerName": "on_isimagetextfound",
				"timestamp": "2024-06-07 13:56:49.570 -0400",
				"scriptName": "Common/check.script",
				"message": "found at (195, 500)",
				"image": "(TEXT:\"Propagation Zone Editor\")",
				"handlerLine": 9,
				"identifier": "imagefound"
			},
		{
				"handlerName": "on_isimagetextfound",
				"timestamp": "2024-06-07 13:56:50.044 -0400",
				"scriptName": "Common/check.script",
				"message": "at (195, 500)",
				"image": "(TEXT:\"Propagation Zone Editor\")",
				"handlerLine": 10,
				"identifier": "moveto"
			},
		{
				"handlerName": "on_success",
				"timestamp": "2024-06-07 13:56:50.095 -0400",
				"message": "Propagation Zone Editor  is found in ToolsMenu",
				"scriptName": "Common/cLog.script",
				"handlerLine": 2,
				"identifier": "LogSuccess"
			},
		{
				"handlerName": "on_clearsearchsection",
				"timestamp": "2024-06-07 13:56:50.175 -0400",
				"message": "SEARCHRECTANGLE = ",
				"scriptName": "Common/search.script",
				"handlerLine": 2,
				"identifier": "set"
			},
		{
				"handlerName": "on_setsearchsection",
				"timestamp": "2024-06-07 13:56:50.576 -0400",
				"message": "SEARCHRECTANGLE = [[96,18.36],[347.52,590.76]]",
				"scriptName": "Common/search.script",
				"handlerLine": 3,
				"identifier": "set"
			},
		{
				"handlerName": "on_isimagetextfound",
				"timestamp": "2024-06-07 13:56:51.085 -0400",
				"scriptName": "Common/check.script",
				"message": "found at (208, 522)",
				"image": "(TEXT:\"Override Configuration Editor\")",
				"handlerLine": 9,
				"identifier": "imagefound"
			},
		{
				"handlerName": "on_isimagetextfound",
				"timestamp": "2024-06-07 13:56:51.631 -0400",
				"scriptName": "Common/check.script",
				"message": "at (208, 522)",
				"image": "(TEXT:\"Override Configuration Editor\")",
				"handlerLine": 10,
				"identifier": "moveto"
			},
		{
				"handlerName": "on_success",
				"timestamp": "2024-06-07 13:56:51.676 -0400",
				"message": "Override Configuration Editor  is found in ToolsMenu",
				"scriptName": "Common/cLog.script",
				"handlerLine": 2,
				"identifier": "LogSuccess"
			},
		{
				"handlerName": "on_clearsearchsection",
				"timestamp": "2024-06-07 13:56:51.735 -0400",
				"message": "SEARCHRECTANGLE = ",
				"scriptName": "Common/search.script",
				"handlerLine": 2,
				"identifier": "set"
			},
		{
				"handlerName": "on_setsearchsection",
				"timestamp": "2024-06-07 13:56:52.107 -0400",
				"message": "SEARCHRECTANGLE = [[96,18.36],[347.52,590.76]]",
				"scriptName": "Common/search.script",
				"handlerLine": 3,
				"identifier": "set"
			},
		{
				"handlerName": "on_isimagetextfound",
				"timestamp": "2024-06-07 13:56:52.575 -0400",
				"scriptName": "Common/check.script",
				"message": "found at (174, 543)",
				"image": "(TEXT:\"Satellite Viewer\")",
				"handlerLine": 9,
				"identifier": "imagefound"
			},
		{
				"handlerName": "on_isimagetextfound",
				"timestamp": "2024-06-07 13:56:53.158 -0400",
				"scriptName": "Common/check.script",
				"message": "at (174, 543)",
				"image": "(TEXT:\"Satellite Viewer\")",
				"handlerLine": 10,
				"identifier": "moveto"
			},
		{
				"handlerName": "on_success",
				"timestamp": "2024-06-07 13:56:53.223 -0400",
				"message": "Satellite Viewer  is found in ToolsMenu",
				"scriptName": "Common/cLog.script",
				"handlerLine": 2,
				"identifier": "LogSuccess"
			},
		{
				"handlerName": "on_clearsearchsection",
				"timestamp": "2024-06-07 13:56:53.281 -0400",
				"message": "SEARCHRECTANGLE = ",
				"scriptName": "Common/search.script",
				"handlerLine": 2,
				"identifier": "set"
			},
		{
				"handlerName": "on_setsearchsection",
				"timestamp": "2024-06-07 13:56:53.647 -0400",
				"message": "SEARCHRECTANGLE = [[96,18.36],[347.52,590.76]]",
				"scriptName": "Common/search.script",
				"handlerLine": 3,
				"identifier": "set"
			},
		{
				"handlerName": "on_isimagetextfound",
				"timestamp": "2024-06-07 13:56:54.156 -0400",
				"scriptName": "Common/check.script",
				"message": "found at (184, 576)",
				"image": "(TEXT:\"Scenario Properties\")",
				"handlerLine": 9,
				"identifier": "imagefound"
			},
		{
				"handlerName": "on_isimagetextfound",
				"timestamp": "2024-06-07 13:56:54.702 -0400",
				"scriptName": "Common/check.script",
				"message": "at (184, 576)",
				"image": "(TEXT:\"Scenario Properties\")",
				"handlerLine": 10,
				"identifier": "moveto"
			},
		{
				"handlerName": "on_success",
				"timestamp": "2024-06-07 13:56:54.747 -0400",
				"message": "Scenario Properties  is found in ToolsMenu",
				"scriptName": "Common/cLog.script",
				"handlerLine": 2,
				"identifier": "LogSuccess"
			},
		{
				"handlerName": "on_clearsearchsection",
				"timestamp": "2024-06-07 13:56:54.812 -0400",
				"message": "SEARCHRECTANGLE = ",
				"scriptName": "Common/search.script",
				"handlerLine": 2,
				"identifier": "set"
			},
		{
				"handlerName": "on_setsearchsection",
				"timestamp": "2024-06-07 13:56:55.183 -0400",
				"message": "SEARCHRECTANGLE = [[96,18.36],[347.52,590.76]]",
				"scriptName": "Common/search.script",
				"handlerLine": 3,
				"identifier": "set"
			},
		{
				"handlerName": "on_leftevent",
				"timestamp": "2024-06-07 13:56:57.101 -0400",
				"scriptName": "Common/clickEvent.script",
				"message": "at (122, 31)",
				"image": "(TEXT:\"Tools\")",
				"handlerLine": 6,
				"identifier": "click"
			},
		{
				"handlerName": "function_isimagetextfound",
				"timestamp": "2024-06-07 13:56:58.721 -0400",
				"scriptName": "Common/check.script",
				"message": "found at (141, 59)",
				"image": "(TEXT:\"Analyzer\")",
				"handlerLine": 9,
				"identifier": "imagefound"
			},
		{
				"handlerName": "function_isimagetextfound",
				"timestamp": "2024-06-07 13:57:00.543 -0400",
				"scriptName": "Common/check.script",
				"message": "at (141, 59)",
				"image": "(TEXT:\"Analyzer\")",
				"handlerLine": 10,
				"identifier": "moveto"
			},
		{
				"handlerName": "on_success",
				"timestamp": "2024-06-07 13:57:00.588 -0400",
				"message": "Analyzer  is found in ",
				"scriptName": "Common/cLog.script",
				"handlerLine": 2,
				"identifier": "LogSuccess"
			},
		{
				"handlerName": "on_clearsearchsection",
				"timestamp": "2024-06-07 13:57:00.656 -0400",
				"message": "SEARCHRECTANGLE = ",
				"scriptName": "Common/search.script",
				"handlerLine": 2,
				"identifier": "set"
			},
		{
				"handlerName": "on_success",
				"timestamp": "2024-06-07 13:57:00.801 -0400",
				"message": "Tools menu closed successfully",
				"scriptName": "Common/cLog.script",
				"handlerLine": 2,
				"identifier": "LogSuccess"
			},
		{
				"handlerName": "on_clearsearchsection",
				"timestamp": "2024-06-07 13:57:00.858 -0400",
				"message": "SEARCHRECTANGLE = ",
				"scriptName": "Common/search.script",
				"handlerLine": 2,
				"identifier": "set"
			},
		{
				"handlerName": "on_setsearchsection",
				"timestamp": "2024-06-07 13:57:01.231 -0400",
				"message": "SEARCHRECTANGLE = [[0,43.2],[96,86.4]]",
				"scriptName": "Common/search.script",
				"handlerLine": 3,
				"identifier": "set"
			},
		{
				"handlerName": "function_isimagetextfound",
				"timestamp": "2024-06-07 13:57:01.462 -0400",
				"scriptName": "Common/check.script",
				"message": "found at (58, 59)",
				"image": "(TEXT:\"Architect\")",
				"handlerLine": 9,
				"identifier": "imagefound"
			},
		{
				"handlerName": "function_isimagetextfound",
				"timestamp": "2024-06-07 13:57:01.894 -0400",
				"scriptName": "Common/check.script",
				"message": "at (58, 59)",
				"image": "(TEXT:\"Architect\")",
				"handlerLine": 10,
				"identifier": "moveto"
			},
		{
				"handlerName": "on_success",
				"timestamp": "2024-06-07 13:57:01.951 -0400",
				"message": "Architect  is found in ArchitectButton",
				"scriptName": "Common/cLog.script",
				"handlerLine": 2,
				"identifier": "LogSuccess"
			},
		{
				"handlerName": "on_clearsearchsection",
				"timestamp": "2024-06-07 13:57:02.012 -0400",
				"message": "SEARCHRECTANGLE = ",
				"scriptName": "Common/search.script",
				"handlerLine": 2,
				"identifier": "set"
			},
		{
				"handlerName": "on_setsearchsection",
				"timestamp": "2024-06-07 13:57:02.389 -0400",
				"message": "SEARCHRECTANGLE = [[0,43.2],[96,86.4]]",
				"scriptName": "Common/search.script",
				"handlerLine": 3,
				"identifier": "set"
			},
		{
				"handlerName": "on_onfoundimagelocation",
				"timestamp": "2024-06-07 13:57:02.633 -0400",
				"scriptName": "Common/clickEvent.script",
				"message": "found at (58, 59)",
				"image": "(TEXT:\"Architect\")",
				"handlerLine": 7,
				"identifier": "imagefound"
			},
		{
				"handlerName": "on_onfoundimagelocation",
				"timestamp": "2024-06-07 13:57:03.032 -0400",
				"message": "at (58, 59)",
				"scriptName": "Common/clickEvent.script",
				"handlerLine": 8,
				"identifier": "click"
			},
		{
				"handlerName": "on_clearsearchsection",
				"timestamp": "2024-06-07 13:57:03.072 -0400",
				"message": "SEARCHRECTANGLE = ",
				"scriptName": "Common/search.script",
				"handlerLine": 2,
				"identifier": "set"
			},
		{
				"handlerName": "on_setsearchsection",
				"timestamp": "2024-06-07 13:57:03.458 -0400",
				"message": "SEARCHRECTANGLE = [[0,0],[249.6,151.2]]",
				"scriptName": "Common/search.script",
				"handlerLine": 3,
				"identifier": "set"
			},
		{
				"handlerName": "on_leftevent",
				"timestamp": "2024-06-07 13:57:04.426 -0400",
				"scriptName": "Common/clickEvent.script",
				"message": "at (14, 31)",
				"image": "(TEXT:\"File\")",
				"handlerLine": 6,
				"identifier": "click"
			},
		{
				"handlerName": "function_isimagetextfound",
				"timestamp": "2024-06-07 13:57:06.124 -0400",
				"scriptName": "Common/check.script",
				"message": "found at (44, 55)",
				"image": "(TEXT:\"New\")",
				"handlerLine": 9,
				"identifier": "imagefound"
			},
		{
				"handlerName": "function_isimagetextfound",
				"timestamp": "2024-06-07 13:57:06.452 -0400",
				"scriptName": "Common/check.script",
				"message": "at (44, 55)",
				"image": "(TEXT:\"New\")",
				"handlerLine": 10,
				"identifier": "moveto"
			},
		{
				"handlerName": "on_success",
				"timestamp": "2024-06-07 13:57:06.498 -0400",
				"message": "New  is found in ",
				"scriptName": "Common/cLog.script",
				"handlerLine": 2,
				"identifier": "LogSuccess"
			},
		{
				"handlerName": "on_clearsearchsection",
				"timestamp": "2024-06-07 13:57:06.560 -0400",
				"message": "SEARCHRECTANGLE = ",
				"scriptName": "Common/search.script",
				"handlerLine": 2,
				"identifier": "set"
			},
		{
				"handlerName": "on_success",
				"timestamp": "2024-06-07 13:57:06.691 -0400",
				"message": "File menu opened successfully",
				"scriptName": "Common/cLog.script",
				"handlerLine": 2,
				"identifier": "LogSuccess"
			},
		{
				"handlerName": "on_capturescreenshots",
				"timestamp": "2024-06-07 13:57:06.829 -0400",
				"scriptName": "Common/captureScreenShots.script",
				"message": "(0,2,808,810)",
				"image": "verifyFileMenu.png",
				"handlerLine": 4,
				"identifier": "capturescreen"
			},
		{
				"handlerName": "on_clearsearchsection",
				"timestamp": "2024-06-07 13:57:06.986 -0400",
				"message": "SEARCHRECTANGLE = ",
				"scriptName": "Common/search.script",
				"handlerLine": 2,
				"identifier": "set"
			},
		{
				"handlerName": "on_setsearchsection",
				"timestamp": "2024-06-07 13:57:07.299 -0400",
				"message": "SEARCHRECTANGLE = [[0,0],[480,270]]",
				"scriptName": "Common/search.script",
				"handlerLine": 3,
				"identifier": "set"
			},
		{
				"handlerName": "on_leftevent",
				"timestamp": "2024-06-07 13:57:08.437 -0400",
				"scriptName": "Common/clickEvent.script",
				"message": "at (53, 208)",
				"image": "(TEXT:\"Close All\")",
				"handlerLine": 6,
				"identifier": "click"
			},
		{
				"handlerName": "on_clearsearchsection",
				"timestamp": "2024-06-07 13:57:08.502 -0400",
				"message": "SEARCHRECTANGLE = ",
				"scriptName": "Common/search.script",
				"handlerLine": 2,
				"identifier": "set"
			},
		{
				"handlerName": "on_compare_screen",
				"timestamp": "2024-06-07 13:57:09.463 -0400",
				"scriptName": "Common/check.script",
				"message": "CompareScreen \"GUI_Canvas_Windows7 6 2024 _ 13 41 18\" -- No significant differences from baseline",
				"image": "[Baseline_Screens]/GUI_Canvas_Windows7 6 2024 _ 13 41 18.png",
				"handlerLine": 3,
				"identifier": "CompareScreen"
			},
		{
				"handlerName": "function_compare_screen",
				"timestamp": "2024-06-07 13:57:09.587 -0400",
				"scriptName": "Common/check.script",
				"message": "CompareScreen \"GUI_Canvas_Windows7 6 2024 _ 13 41 18\" -- No significant differences from baseline",
				"image": "[Baseline_Screens]/GUI_Canvas_Windows7 6 2024 _ 13 41 18.png",
				"handlerLine": 3,
				"identifier": "CompareScreen"
			},
		{
				"handlerName": "on_clickscaled",
				"timestamp": "2024-06-07 13:57:11.792 -0400",
				"message": "at (960, 540)",
				"scriptName": "Common/clickEvent.script",
				"handlerLine": 3,
				"identifier": "click"
			},
		{
				"handlerName": "on_verifytoolsmenu",
				"timestamp": "2024-06-07 13:57:11.852 -0400",
				"message": "(Duration:\"57.319\", Errors:\"0\", Exceptions:\"0\", StartTime:\"2024-06-07 13:56:14 -0400\", Successes:\"30\", TestCase:\"verifyToolsMenu\", Warnings:\"0\")",
				"scriptName": "TestCases/Regular/verifyToolsMenu.script",
				"handlerLine": 87,
				"identifier": "EndTestCase"
			},
		{
				"handlerName": "on_startregulartests",
				"timestamp": "2024-06-07 13:57:11.883 -0400",
				"message": "(Duration:\"57.402\", Errors:\"0\", Exceptions:\"0\", StartTime:\"2024-06-07 13:56:14 -0400\", Successes:\"30\", TestCase:\"TestCases/Regular/verifyToolsMenu.script\", Warnings:\"0\")",
				"scriptName": "TestCases/Regular/testLauncher.script",
				"handlerLine": 22,
				"identifier": "EndTestCase"
			},
		{
				"handlerName": "on_startregulartests",
				"timestamp": "2024-06-07 13:57:11.936 -0400",
				"message": "Execution Time 0:00:57 TestCases/Regular/verifyToolsMenu.script",
				"scriptName": "TestCases/Regular/testLauncher.script",
				"handlerLine": 22,
				"identifier": "SUCCESS"
			}
	],
	"createdTimestamp": "2024-06-07 13:56:14.481 -0400"
}